{
	"info": {
		"_postman_id": "fe25fc48-caa5-4feb-a47d-2d51b80a1936",
		"name": "teste-stoom",
		"schema": "https://schema.getpostman.com/json/collection/v2.1.0/collection.json",
		"_exporter_id": "10962643",
		"_collection_link": "https://dark-meteor-605902.postman.co/workspace/testes-vaga~5f9cb0b3-ce9a-456d-b78c-5634aae13ae2/collection/10962643-fe25fc48-caa5-4feb-a47d-2d51b80a1936?action=share&source=collection_link&creator=10962643"
	},
	"item": [
		{
			"name": "Category",
			"item": [
				{
					"name": "Get All Categories",
					"request": {
						"method": "GET",
						"header": [],
						"url": {
							"raw": "http://localhost:8082/api/category/",
							"protocol": "http",
							"host": [
								"localhost"
							],
							"port": "8082",
							"path": [
								"api",
								"category",
								""
							]
						}
					},
					"response": []
				},
				{
					"name": "GetAllCategoriesById",
					"request": {
						"method": "GET",
						"header": [],
						"url": {
							"raw": "http://localhost:8082/api/category/1",
							"protocol": "http",
							"host": [
								"localhost"
							],
							"port": "8082",
							"path": [
								"api",
								"category",
								"1"
							]
						}
					},
					"response": []
				},
				{
					"name": "DeleteCategory",
					"request": {
						"method": "PATCH",
						"header": [],
						"url": {
							"raw": "http://localhost:8082/api/category/delete/1",
							"protocol": "http",
							"host": [
								"localhost"
							],
							"port": "8082",
							"path": [
								"api",
								"category",
								"delete",
								"1"
							]
						}
					},
					"response": []
				},
				{
					"name": "Save Category",
					"request": {
						"method": "POST",
						"header": [
							{
								"key": "Content-Type",
								"value": "application/json",
								"type": "text"
							}
						],
						"body": {
							"mode": "raw",
							"raw": "{\n  \"name\": \"string\",\n  \"description\": \"string\"\n}",
							"options": {
								"raw": {
									"language": "json"
								}
							}
						},
						"url": {
							"raw": "http://localhost:8082/api/category/",
							"protocol": "http",
							"host": [
								"localhost"
							],
							"port": "8082",
							"path": [
								"api",
								"category",
								""
							]
						}
					},
					"response": []
				}
			]
		},
		{
			"name": "Product",
			"item": [
				{
					"name": "GetProductById",
					"request": {
						"method": "GET",
						"header": [],
						"url": {
							"raw": "http://localhost:8082/api/products/1",
							"protocol": "http",
							"host": [
								"localhost"
							],
							"port": "8082",
							"path": [
								"api",
								"products",
								"1"
							]
						}
					},
					"response": []
				},
				{
					"name": "GetAllProducts",
					"request": {
						"method": "GET",
						"header": [],
						"url": {
							"raw": "http://localhost:8082/api/products/",
							"protocol": "http",
							"host": [
								"localhost"
							],
							"port": "8082",
							"path": [
								"api",
								"products",
								""
							]
						}
					},
					"response": []
				},
				{
					"name": "DeleteProduct",
					"request": {
						"method": "PATCH",
						"header": [],
						"url": {
							"raw": "http://localhost:8082/api/products/delete/1",
							"protocol": "http",
							"host": [
								"localhost"
							],
							"port": "8082",
							"path": [
								"api",
								"products",
								"delete",
								"1"
							]
						}
					},
					"response": []
				},
				{
					"name": "Save Product",
					"request": {
						"method": "PATCH",
						"header": [
							{
								"key": "Content-Type",
								"value": "application/json",
								"type": "text"
							}
						],
						"body": {
							"mode": "raw",
							"raw": "{\n        \"id\": 1,\n        \"sku\": \"SKU1\",\n        \"name\": \"Smart TV 40 pol\",\n        \"category\": 1,\n        \"brand\": 1,\n        \"price\": 10.50\n    }",
							"options": {
								"raw": {
									"language": "json"
								}
							}
						},
						"url": {
							"raw": "http://localhost:8082/api/products/",
							"protocol": "http",
							"host": [
								"localhost"
							],
							"port": "8082",
							"path": [
								"api",
								"products",
								""
							]
						}
					},
					"response": []
				}
			]
		},
		{
			"name": "Brand",
			"item": [
				{
					"name": "GetAllBrands",
					"request": {
						"method": "GET",
						"header": [],
						"url": {
							"raw": "http://localhost:8082/api/brand/",
							"protocol": "http",
							"host": [
								"localhost"
							],
							"port": "8082",
							"path": [
								"api",
								"brand",
								""
							]
						}
					},
					"response": []
				},
				{
					"name": "GetBrandById",
					"request": {
						"method": "GET",
						"header": [],
						"url": {
							"raw": "http://localhost:8082/api/brand/3",
							"protocol": "http",
							"host": [
								"localhost"
							],
							"port": "8082",
							"path": [
								"api",
								"brand",
								"3"
							]
						}
					},
					"response": []
				},
				{
					"name": "DeleteBrand",
					"request": {
						"method": "PATCH",
						"header": [],
						"url": {
							"raw": "http://localhost:8082/api/brand/delete/1",
							"protocol": "http",
							"host": [
								"localhost"
							],
							"port": "8082",
							"path": [
								"api",
								"brand",
								"delete",
								"1"
							]
						}
					},
					"response": []
				},
				{
					"name": "Save Brand",
					"request": {
						"method": "POST",
						"header": [
							{
								"key": "Content-Type",
								"value": "application/json",
								"type": "text"
							}
						],
						"body": {
							"mode": "raw",
							"raw": "{\n  \"description\": \"string\",\n  \"name\": \"string\"\n}",
							"options": {
								"raw": {
									"language": "json"
								}
							}
						},
						"url": {
							"raw": "http://localhost:8082/api/brand/",
							"protocol": "http",
							"host": [
								"localhost"
							],
							"port": "8082",
							"path": [
								"api",
								"brand",
								""
							]
						}
					},
					"response": []
				}
			]
		}
	]
}